vivado_xpr_fixer/__init__.py
vivado_xpr_fixer/vivado_xpr_fixer.py
vivado_xpr_fixer-1.0.0.dist-info/LICENCE
vivado_xpr_fixer-1.0.0.dist-info/METADATA
vivado_xpr_fixer-1.0.0.dist-info/WHEEL
vivado_xpr_fixer-1.0.0.dist-info/entry_points.txt
vivado_xpr_fixer-1.0.0.dist-info/top_level.txt
vivado_xpr_fixer-1.0.0.dist-info/RECORD
