Metadata-Version: 2.1
Name: vivado-xpr-fixer
Version: 1.0.0
Summary: A script to fix Vivado absolute path issues when working with git.
Home-page: https://github.com/JosiahCraw/vivado-xpr-fixer
Author: Jesse Shehan
Author-email: jps111@uclive.ac.nz
License: UNKNOWN
Platform: UNKNOWN
Classifier: Programming Language :: Python :: 3
Classifier: License :: OSI Approved :: MIT License
Classifier: Operating System :: OS Independent
Requires-Python: >=3.6
